docdb_import_export/.env.example
docdb_import_export/__init__.py
docdb_import_export/__main__.py
docdb_import_export/docdb_client.py
docdb_import_export/docdb_json_importer.py
docdb_import_export/utils.py
docdb_import_export-0.6.2.dist-info/METADATA
docdb_import_export-0.6.2.dist-info/WHEEL
docdb_import_export-0.6.2.dist-info/licenses/LICENSE
docdb_import_export-0.6.2.dist-info/RECORD
