Metadata-Version: 2.1
Name: docdb-import-export
Version: 0.6.2
Summary: A simple utility package to import json files to document db and export data from document db collections.
Project-URL: Homepage, https://github.com/msankhala/docdb-import-export
Project-URL: Bug Tracker, https://github.com/msankhala/docdb-import-export/issues
Author-email: Mahesh Sankhala <maheshsainni@gmail.com>
License-File: LICENSE
Classifier: License :: OSI Approved :: MIT License
Classifier: Operating System :: OS Independent
Classifier: Programming Language :: Python :: 3
Requires-Python: >=3.8
Requires-Dist: pymongo>=4.5.0
Requires-Dist: python-dotenv>=1.0.0
